README.md
setup.py
pykuna/__init__.py
pykuna/camera.py
pykuna/errors.py
pykuna/kuna.py
pykuna/recording.py
pykuna.egg-info/PKG-INFO
pykuna.egg-info/SOURCES.txt
pykuna.egg-info/dependency_links.txt
pykuna.egg-info/requires.txt
pykuna.egg-info/top_level.txt