Metadata-Version: 2.1
Name: pykuna
Version: 0.5.1
Summary: Python3 library for interacting with the Kuna camera mobile API
Home-page: https://github.com/marthoc/pykuna
Author: Mark Coombes
Author-email: mark@markcoombes.ca
License: UNKNOWN
Platform: UNKNOWN
Classifier: Intended Audience :: Developers
Classifier: Programming Language :: Python
Classifier: Programming Language :: Python :: 3
Classifier: License :: OSI Approved :: MIT License
Classifier: Operating System :: OS Independent
Classifier: Topic :: Software Development :: Libraries :: Python Modules
